sentinelx/__init__.py
sentinelx/cli.py
sentinelx/assets/logo.png
sentinelx/assets/logo.svg
sentinelx/banner/banner.txt
sentinelx/config/tools.yaml
sentinelx/core/__init__.py
sentinelx/core/advanced_reporting.py
sentinelx/core/checker.py
sentinelx/core/dashboard.py
sentinelx/core/executor.py
sentinelx/core/logger.py
sentinelx/core/logo_gen.py
sentinelx/core/menu.py
sentinelx/core/mitre.py
sentinelx/core/pdf_gen.py
sentinelx/core/reporting.py
sentinelx/core/ui.py
sentinelx/modules/__init__.py
sentinelx/modules/blue/__init__.py
sentinelx/modules/blue/logs.py
sentinelx/modules/blue/scan.py
sentinelx/modules/purple/__init__.py
sentinelx/modules/purple/simulation.py
sentinelx/modules/red/__init__.py
sentinelx/modules/red/auth.py
sentinelx/modules/red/payload.py
sentinelx/modules/red/recon.py
sentinelx/modules/red/web.py
sentinelx-2.4.0.dist-info/licenses/LICENSE.md
sentinelx-2.4.0.dist-info/METADATA
sentinelx-2.4.0.dist-info/WHEEL
sentinelx-2.4.0.dist-info/entry_points.txt
sentinelx-2.4.0.dist-info/top_level.txt
sentinelx-2.4.0.dist-info/RECORD
