Metadata-Version: 2.4
Name: sentinelx
Version: 2.4.0
Summary: SentinelX - Red/Blue/Purple Team Security Framework
Home-page: https://github.com/hackura/SentinelX
Author: Hackura
Classifier: Programming Language :: Python :: 3
Classifier: Operating System :: POSIX :: Linux
Classifier: Topic :: Security
Classifier: License :: OSI Approved :: MIT License
Requires-Python: >=3.8
License-File: LICENSE.md
Requires-Dist: rich>=13.0.0
Requires-Dist: pyyaml>=6.0
Requires-Dist: requests>=2.31.0
Requires-Dist: jinja2>=3.1.0
Requires-Dist: reportlab>=4.0.0
Provides-Extra: pdf
Requires-Dist: weasyprint>=60.0; extra == "pdf"
Requires-Dist: svglib>=1.5.0; extra == "pdf"
Dynamic: author
Dynamic: classifier
Dynamic: description
Dynamic: description-content-type
Dynamic: home-page
Dynamic: license-file
Dynamic: provides-extra
Dynamic: requires-dist
Dynamic: requires-python
Dynamic: summary
